requirements.txt
staphb-tk
workflows.json
staphb_toolkit/__init__.py
staphb_toolkit/toolkit_main.py
staphb_toolkit/config/docker.config
staphb_toolkit/config/singularity.config
staphb_toolkit/lib/VERSION
staphb_toolkit/lib/__init__.py
staphb_toolkit/lib/autopath.py
staphb_toolkit/lib/calldocker.py
staphb_toolkit/lib/callnextflow.py
staphb_toolkit/lib/callsing.py
staphb_toolkit/lib/container_handler.py
staphb_toolkit/lib/updates.py
staphb_toolkit-2.0.1.dist-info/LICENSE
staphb_toolkit-2.0.1.dist-info/METADATA
staphb_toolkit-2.0.1.dist-info/WHEEL
staphb_toolkit-2.0.1.dist-info/entry_points.txt
staphb_toolkit-2.0.1.dist-info/top_level.txt
staphb_toolkit-2.0.1.dist-info/RECORD
