Metadata-Version: 2.1
Name: staphb-toolkit
Version: 2.0.1
Summary: A ToolKit of commonly used Public Health Bioinformatics Tools
Home-page: https://github.com/StaPH-B/staphb_toolkit
Author: Kelsey Florek
Author-email: kelsey.florek@slh.wisc.edu
Classifier: Programming Language :: Python :: 3
Classifier: License :: OSI Approved :: GNU General Public License v3 (GPLv3)
Classifier: Operating System :: OS Independent
Requires-Python: >=3.7
License-File: LICENSE
Requires-Dist: spython (>=0.0.73)
Requires-Dist: psutil (>=5.6.3)
Requires-Dist: docker (>=4.1.0)
Requires-Dist: pexpect (>=4.8)
Requires-Dist: pyfiglet (>=0.8.post1)
Requires-Dist: rich (>=12.4.4)
